kerasAC/__init__.py
kerasAC/__main__.py
kerasAC/abstention.py
kerasAC/accuracy_metrics.py
kerasAC/activations.py
kerasAC/basset_architecture.original.py
kerasAC/basset_architecture_multitask.py
kerasAC/basset_architecture_single_task.py
kerasAC/calibrate.py
kerasAC/chrom_to_split.py
kerasAC/config.py
kerasAC/create_generators.py
kerasAC/cross_validate.py
kerasAC/curves.py
kerasAC/custom_callbacks.py
kerasAC/custom_losses.py
kerasAC/draw_PRC_and_ROC.py
kerasAC/generators.py
kerasAC/get_model.py
kerasAC/get_model_predictions.py
kerasAC/gpu.py
kerasAC/gradient_input.py
kerasAC/interpret.py
kerasAC/metrics.py
kerasAC/performance_metrics.py
kerasAC/plot_interpretation.py
kerasAC/predict.py
kerasAC/predict_hdf5.py
kerasAC/predict_tiledb.py
kerasAC/profile_performance_metrics.py
kerasAC/runModelPureKeras.py
kerasAC/s3_sync.py
kerasAC/splits.py
kerasAC/tdb_config.py
kerasAC/test.py
kerasAC/test_genome_placeholder.py
kerasAC/test_one_hot_from_bed.py
kerasAC/test_preallocate_genome_df.py
kerasAC/tiledb_config.py
kerasAC/tiledb_generators.py
kerasAC/tiledb_predict.py
kerasAC/train.py
kerasAC/unit_test_var_seqs.py
kerasAC/util.py
kerasAC/architectures/__init__.py
kerasAC/architectures/basset_architecture.py
kerasAC/architectures/basset_architecture_multitask.py
kerasAC/architectures/battnet.py
kerasAC/architectures/functional_basset.py
kerasAC/architectures/functional_basset_multitask.py
kerasAC/architectures/functional_basset_singletask.py
kerasAC/architectures/functional_fbasset.py
kerasAC/architectures/functional_regression.py
kerasAC/architectures/model_test.py
kerasAC/architectures/profile_model.py
kerasAC/architectures/regression.py
kerasAC/architectures/resnet.py
kerasAC/architectures/resnet_simple.py
kerasAC/architectures/resnet_simple_full_preactivation.py
kerasAC/architectures/tf_chipseq_classification.py
kerasAC/architectures/tf_chipseq_regression.py
kerasAC/architectures/__pycache__/regression.cpython-36.pyc
kerasAC/architectures/__pycache__/resnet.cpython-36.pyc
kerasAC-2.5.4.dist-info/LICENSE
kerasAC-2.5.4.dist-info/METADATA
kerasAC-2.5.4.dist-info/WHEEL
kerasAC-2.5.4.dist-info/entry_points.txt
kerasAC-2.5.4.dist-info/top_level.txt
kerasAC-2.5.4.dist-info/RECORD
