Metadata-Version: 2.1
Name: kerasAC
Version: 2.5.4
Summary: keras Accessibility Models (kerasAC)
Home-page: UNKNOWN
Author: UNKNOWN
Author-email: UNKNOWN
License: UNKNOWN
Download-URL: https://github.com/kundajelab/kerasAC
Platform: UNKNOWN
Requires-Dist: tensorflow-gpu (>=2.3)
Requires-Dist: pysam
Requires-Dist: tiledb (>=0.5.2)
Requires-Dist: psutil
Requires-Dist: tables
Requires-Dist: numpy (>=1.9)
Requires-Dist: keras (>=2.4)
Requires-Dist: h5py
Requires-Dist: pandas
Requires-Dist: pybigwig
Requires-Dist: deeplift
Requires-Dist: abstention
Requires-Dist: boto3
